shallow_backup/__init__.py
shallow_backup/__main__.py
shallow_backup/backup.py
shallow_backup/compatibility.py
shallow_backup/config.py
shallow_backup/constants.py
shallow_backup/git_wrapper.py
shallow_backup/printing.py
shallow_backup/prompts.py
shallow_backup/reinstall.py
shallow_backup/utils.py
shallow_backup-2.8.dist-info/LICENSE
shallow_backup-2.8.dist-info/METADATA
shallow_backup-2.8.dist-info/WHEEL
shallow_backup-2.8.dist-info/entry_points.txt
shallow_backup-2.8.dist-info/top_level.txt
shallow_backup-2.8.dist-info/RECORD
