Metadata-Version: 2.1
Name: shallow-backup
Version: 2.8
Summary: Easily create lightweight backups of installed packages, dotfiles, and more.
Home-page: https://github.com/alichtman/shallow-backup
Author: alichtman
Author-email: aaronlichtman@gmail.com
License: UNKNOWN
Project-URL: Bug Reports, https://github.com/alichtman/shallow-backup/issues
Project-URL: Donations, https://www.patreon.com/alichtman
Keywords: backup documentation system dotfiles install list configuration
Platform: UNKNOWN
Classifier: Development Status :: 4 - Beta
Classifier: Environment :: MacOS X
Classifier: Intended Audience :: Developers
Classifier: Intended Audience :: End Users/Desktop
Classifier: Intended Audience :: System Administrators
Classifier: Topic :: System :: Installation/Setup
Classifier: Topic :: System :: Archiving :: Backup
Classifier: Topic :: System :: Operating System
Classifier: Topic :: Documentation
Classifier: Topic :: Utilities
Classifier: Operating System :: MacOS
Classifier: Operating System :: POSIX :: Linux
Classifier: Operating System :: Unix
Classifier: Natural Language :: English
Classifier: License :: OSI Approved :: MIT License
Classifier: Programming Language :: Python :: 3
Classifier: Programming Language :: Python :: 3.4
Classifier: Programming Language :: Python :: 3.5
Classifier: Programming Language :: Python :: 3.6
Classifier: Programming Language :: Python :: 3.7
Requires-Dist: inquirer (>=2.2.0)
Requires-Dist: colorama (>=0.3.9)
Requires-Dist: gitpython
Requires-Dist: Click
